keshik/DDPM_model.py
keshik/__init__.py
keshik/oversampler.py
keshik/traindiffusion_byColumns.py
keshik/traindiffusion_byMatrix.py
keshik/traindiffusion_byRows.py
keshik-0.0.5.dist-info/LICENSE
keshik-0.0.5.dist-info/METADATA
keshik-0.0.5.dist-info/WHEEL
keshik-0.0.5.dist-info/top_level.txt
keshik-0.0.5.dist-info/RECORD
